gaugesrv/.index.scss.swp
gaugesrv/__init__.py
gaugesrv/app.py
gaugesrv/index.scss
gaugesrv/lib.js
gaugesrv/static/index.html
gaugesrv/tests/__init__.py
gaugesrv/tests/test_gaugesrv.js
gaugesrv/tests/test_gaugesrv.py
gaugesrv-0.0.1.dist-info/METADATA
gaugesrv-0.0.1.dist-info/RECORD
gaugesrv-0.0.1.dist-info/WHEEL
gaugesrv-0.0.1.dist-info/calmjs_artifacts.json
gaugesrv-0.0.1.dist-info/calmjs_module_registry.txt
gaugesrv-0.0.1.dist-info/calmjs_scss_module_registry.txt
gaugesrv-0.0.1.dist-info/entry_points.txt
gaugesrv-0.0.1.dist-info/extras_calmjs.json
gaugesrv-0.0.1.dist-info/namespace_packages.txt
gaugesrv-0.0.1.dist-info/package.json
gaugesrv-0.0.1.dist-info/top_level.txt
gaugesrv-0.0.1.dist-info/calmjs_artifacts/styles.css
gaugesrv-0.0.1.dist-info/calmjs_artifacts/styles.min.css
gaugesrv-0.0.1.dist-info/calmjs_artifacts/webpack.js
gaugesrv-0.0.1.dist-info/calmjs_artifacts/webpack.min.js
