Metadata-Version: 2.1
Name: gaugesrv
Version: 0.0.1
Summary: A silly service for serving gauges to browsers
Home-page: https://github.com/metatoaster/gaugesrv
Author: Tommy Yu
Author-email: y@metatoaster.com
License: GPL
Platform: UNKNOWN
Classifier: Development Status :: 4 - Beta
Classifier: License :: OSI Approved :: GNU General Public License v2 or later (GPLv2+)
Classifier: Operating System :: OS Independent
Classifier: Programming Language :: JavaScript
Classifier: Programming Language :: Python
Classifier: Programming Language :: Python :: 3.4
Classifier: Programming Language :: Python :: 3.5
Classifier: Programming Language :: Python :: 3.6
Classifier: Programming Language :: Python :: Implementation :: CPython
Classifier: Programming Language :: Python :: Implementation :: PyPy
Classifier: Topic :: Utilities
Requires-Python: >=3.4
Provides-Extra: scss
Provides-Extra: dev
Provides-Extra: webpack
Provides-Extra: rjs
Requires-Dist: sanic
Provides-Extra: dev
Requires-Dist: calmjs.dev; extra == 'dev'
Requires-Dist: aiohttp; extra == 'dev'
Provides-Extra: rjs
Requires-Dist: calmjs.rjs; extra == 'rjs'
Provides-Extra: scss
Requires-Dist: calmjs.sassy[libsass]; extra == 'scss'
Provides-Extra: webpack
Requires-Dist: calmjs.webpack; extra == 'webpack'
